sso_nebus/__init__.py
sso_nebus/base.py
sso_nebus/exceptions.py
sso_nebus/exmples/example_admin.py
sso_nebus/exmples/example_service.py
sso_nebus/exmples/example_user.py
sso_nebus/models.py
sso_nebus/service_client.py
sso_nebus/user_client.py
sso_nebus-0.1.4.dist-info/licenses/LICENSE
sso_nebus-0.1.4.dist-info/METADATA
sso_nebus-0.1.4.dist-info/WHEEL
sso_nebus-0.1.4.dist-info/RECORD
