Metadata-Version: 2.4
Name: sso-nebus
Version: 0.1.4
Summary: Python клиент для взаимодействия с MS Auth Service API
License: LICENSE
License-File: LICENSE
Author: Артем Костюченко
Author-email: kostyuchenko.work@gmail.com
Requires-Python: >=3.12
Classifier: License :: Other/Proprietary License
Classifier: Programming Language :: Python :: 3
Classifier: Programming Language :: Python :: 3.12
Classifier: Programming Language :: Python :: 3.13
Classifier: Programming Language :: Python :: 3.14
Requires-Dist: aiohttp (>=3.13.2,<4.0.0)
Requires-Dist: pydantic (>=2.12.5,<3.0.0)
